{
    "batch_1": {
        "orders": [
            "8",
            "20",
            "62",
            "77",
            "104",
            "119",
            "128",
            "155",
            "164",
            "176",
            "179",
            "194",
            "218",
            "239",
            "245",
            "266",
            "287",
            "329",
            "368",
            "383",
            "386",
            "428",
            "446",
            "455",
            "461",
            "473",
            "551",
            "557"
        ],
        "pickRoute": [
            "1864",
            "940",
            "1881",
            "1949",
            "572",
            "1481",
            "465",
            "470",
            "2163",
            "2116",
            "905",
            "1629",
            "122",
            "1861",
            "1103",
            "1218",
            "570",
            "445",
            "2030",
            "1427",
            "1048",
            "496",
            "701",
            "2026",
            "1541",
            "1164",
            "1320",
            "1645",
            "1653",
            "1265",
            "1501",
            "1242",
            "483",
            "1271",
            "1317",
            "2",
            "24",
            "47",
            "1533",
            "997",
            "977",
            "1093",
            "1977",
            "1067",
            "281",
            "1001",
            "1513",
            "1177"
        ],
        "SKUs": [
            "584",
            "33",
            "605",
            "202",
            "337",
            "365",
            "160",
            "713",
            "840",
            "579",
            "499",
            "118",
            "94",
            "831",
            "406",
            "689",
            "364",
            "585",
            "841",
            "240",
            "500",
            "161",
            "185",
            "298",
            "647",
            "241",
            "714",
            "676",
            "32",
            "830",
            "201",
            "254",
            "13",
            "95",
            "119",
            "698",
            "271",
            "276",
            "438",
            "253",
            "338",
            "299",
            "270",
            "557",
            "580",
            "646",
            "437",
            "373"
        ],
        "distance": 230.322265625,
        "computational_time": 221.371364
    },
    "batch_2": {
        "orders": [
            "16",
            "127",
            "133",
            "139",
            "411",
            "454",
            "538"
        ],
        "pickRoute": [
            "1951",
            "1691",
            "339",
            "538",
            "494",
            "1776",
            "308",
            "1756",
            "454",
            "34",
            "2101",
            "2052",
            "1534"
        ],
        "SKUs": [
            "26",
            "199",
            "687",
            "210",
            "209",
            "27",
            "200",
            "812",
            "620",
            "219",
            "220",
            "811",
            "688"
        ],
        "distance": 125.04296875,
        "computational_time": 222.48418
    },
    "batch_3": {
        "orders": [
            "22",
            "40",
            "55",
            "64",
            "100",
            "151",
            "157",
            "166",
            "190",
            "196",
            "235",
            "283",
            "292",
            "334",
            "367",
            "370",
            "377",
            "409",
            "433",
            "469",
            "472",
            "481",
            "521",
            "523",
            "532",
            "541",
            "547",
            "562"
        ],
        "pickRoute": [
            "1837",
            "170",
            "710",
            "373",
            "1134",
            "173",
            "921",
            "17",
            "1529",
            "1308",
            "714",
            "1167",
            "25",
            "1450",
            "915",
            "477",
            "457",
            "2136",
            "1894",
            "354",
            "2063",
            "1841",
            "1187",
            "1441",
            "1406",
            "534",
            "514",
            "2037",
            "1731",
            "1163"
        ],
        "SKUs": [
            "236",
            "712",
            "789",
            "359",
            "301",
            "82",
            "507",
            "431",
            "559",
            "445",
            "815",
            "655",
            "98",
            "824",
            "293",
            "801",
            "556",
            "62",
            "709",
            "257",
            "618",
            "848",
            "155",
            "81",
            "243",
            "570",
            "787",
            "36",
            "727",
            "235"
        ],
        "distance": 109.21875,
        "computational_time": 220.863354
    },
    "batch_4": {
        "orders": [
            "18",
            "44",
            "48",
            "49",
            "69",
            "84",
            "108",
            "120",
            "186",
            "223",
            "228",
            "234",
            "312",
            "330",
            "333",
            "342",
            "345",
            "348",
            "378",
            "397",
            "403",
            "405",
            "420",
            "453",
            "471",
            "483",
            "513",
            "577"
        ],
        "pickRoute": [
            "457",
            "1946",
            "1646",
            "1248",
            "1918",
            "1552",
            "44",
            "1840",
            "230",
            "1673",
            "854",
            "1315",
            "968",
            "1370",
            "1490",
            "1321",
            "781",
            "1066",
            "2046",
            "300",
            "1404",
            "1512",
            "1733",
            "745",
            "39",
            "426",
            "1280",
            "1971",
            "1618",
            "1517",
            "577",
            "303",
            "1261",
            "906",
            "278",
            "930",
            "1453"
        ],
        "SKUs": [
            "556",
            "610",
            "105",
            "686",
            "128",
            "613",
            "72",
            "867",
            "358",
            "527",
            "474",
            "633",
            "518",
            "776",
            "473",
            "186",
            "286",
            "506",
            "522",
            "658",
            "775",
            "351",
            "711",
            "602",
            "67",
            "572",
            "501",
            "167",
            "517",
            "571",
            "730",
            "29",
            "73",
            "566",
            "66",
            "344",
            "603"
        ],
        "distance": 221.990234375,
        "computational_time": 222.191662
    },
    "batch_5": {
        "orders": [
            "60",
            "81",
            "102",
            "141",
            "144",
            "150",
            "169",
            "174",
            "198",
            "220",
            "252",
            "258",
            "318",
            "354",
            "357",
            "360",
            "363",
            "381",
            "384",
            "391",
            "432",
            "456",
            "486",
            "507",
            "522",
            "558",
            "561",
            "585"
        ],
        "pickRoute": [
            "1999",
            "1233",
            "1966",
            "1795",
            "1447",
            "1447",
            "1138",
            "797",
            "2086",
            "981",
            "401",
            "401",
            "335",
            "282",
            "381",
            "544",
            "1612",
            "731",
            "337",
            "741",
            "1477",
            "1575",
            "327",
            "893",
            "1298",
            "391",
            "424",
            "424",
            "1300",
            "754",
            "1931",
            "205",
            "2071",
            "852",
            "904",
            "1229",
            "1978",
            "875",
            "309",
            "1090",
            "1749",
            "157",
            "1924",
            "1608",
            "664"
        ],
        "SKUs": [
            "392",
            "340",
            "222",
            "765",
            "593",
            "593",
            "880",
            "842",
            "550",
            "691",
            "233",
            "233",
            "581",
            "541",
            "576",
            "227",
            "547",
            "304",
            "481",
            "385",
            "847",
            "654",
            "305",
            "267",
            "90",
            "535",
            "788",
            "788",
            "157",
            "482",
            "124",
            "226",
            "536",
            "653",
            "393",
            "234",
            "546",
            "733",
            "846",
            "766",
            "734",
            "540",
            "91",
            "690",
            "261"
        ],
        "distance": 249.037109375,
        "computational_time": 221.729352
    },
    "batch_6": {
        "orders": [
            "3",
            "6",
            "36",
            "54",
            "67",
            "72",
            "75",
            "83",
            "91",
            "97",
            "99",
            "138",
            "162",
            "171",
            "231",
            "241",
            "277",
            "288",
            "297",
            "324",
            "336",
            "339",
            "387",
            "468",
            "487",
            "495",
            "516",
            "554"
        ],
        "pickRoute": [
            "443",
            "967",
            "656",
            "1085",
            "1385",
            "979",
            "1663",
            "796",
            "1273",
            "1424",
            "627",
            "1668",
            "1399",
            "1399",
            "33",
            "200",
            "1089",
            "581",
            "644",
            "644",
            "20",
            "1961",
            "294",
            "1243",
            "1419",
            "658",
            "1472",
            "1472",
            "670",
            "1270",
            "640",
            "1010",
            "1152",
            "2054",
            "242",
            "1094",
            "598",
            "761",
            "1303",
            "1936",
            "1856",
            "1165",
            "259",
            "762",
            "1525",
            "1104",
            "1312",
            "1526"
        ],
        "SKUs": [
            "140",
            "102",
            "367",
            "150",
            "421",
            "735",
            "103",
            "139",
            "439",
            "10",
            "5",
            "250",
            "780",
            "780",
            "57",
            "79",
            "749",
            "451",
            "127",
            "127",
            "510",
            "587",
            "154",
            "677",
            "115",
            "708",
            "513",
            "513",
            "354",
            "109",
            "491",
            "80",
            "750",
            "452",
            "153",
            "251",
            "781",
            "114",
            "440",
            "707",
            "490",
            "263",
            "586",
            "264",
            "218",
            "126",
            "836",
            "835"
        ],
        "distance": 281.025390625,
        "computational_time": 220.668865
    },
    "batch_7": {
        "orders": [
            "9",
            "12",
            "21",
            "30",
            "51",
            "93",
            "111",
            "135",
            "189",
            "204",
            "221",
            "240",
            "270",
            "276",
            "322",
            "414",
            "441",
            "444",
            "462",
            "475",
            "480",
            "492",
            "504",
            "540",
            "549",
            "564",
            "573",
            "590"
        ],
        "pickRoute": [
            "792",
            "199",
            "1508",
            "202",
            "1008",
            "1604",
            "478",
            "584",
            "584",
            "976",
            "1962",
            "2070",
            "2070",
            "472",
            "472",
            "1311",
            "965",
            "442",
            "43",
            "79",
            "943",
            "805",
            "116",
            "2113",
            "1180",
            "1378",
            "174",
            "745",
            "574",
            "629",
            "1473",
            "1467",
            "1467",
            "1486",
            "2169",
            "98",
            "743",
            "1356",
            "1383",
            "951",
            "1405",
            "1954",
            "430",
            "1969",
            "1046",
            "406",
            "498",
            "1915",
            "568"
        ],
        "SKUs": [
            "487",
            "411",
            "717",
            "171",
            "745",
            "420",
            "366",
            "827",
            "827",
            "35",
            "314",
            "863",
            "863",
            "291",
            "291",
            "292",
            "34",
            "744",
            "14",
            "143",
            "419",
            "61",
            "454",
            "447",
            "213",
            "668",
            "674",
            "602",
            "47",
            "172",
            "826",
            "673",
            "673",
            "669",
            "623",
            "212",
            "850",
            "75",
            "20",
            "46",
            "726",
            "144",
            "814",
            "699",
            "760",
            "15",
            "886",
            "341",
            "718"
        ],
        "distance": 278.271484375,
        "computational_time": 221.47979
    },
    "batch_8": {
        "orders": [
            "46",
            "82",
            "88",
            "148",
            "184",
            "205",
            "265",
            "295",
            "298",
            "301",
            "310",
            "337",
            "355",
            "394",
            "400",
            "406",
            "412",
            "427",
            "448",
            "451",
            "478",
            "484",
            "496",
            "502",
            "508",
            "526",
            "553",
            "592"
        ],
        "pickRoute": [
            "2032",
            "699",
            "243",
            "2091",
            "1227",
            "1296",
            "1247",
            "2121",
            "306",
            "1686",
            "438",
            "1079",
            "1121",
            "104",
            "2094",
            "1788",
            "614",
            "146",
            "736",
            "767",
            "673",
            "476",
            "7",
            "1434",
            "1082",
            "439",
            "81",
            "846",
            "1113",
            "341",
            "132"
        ],
        "SKUs": [
            "315",
            "679",
            "70",
            "470",
            "645",
            "834",
            "453",
            "621",
            "767",
            "683",
            "284",
            "731",
            "134",
            "537",
            "469",
            "723",
            "644",
            "448",
            "678",
            "597",
            "231",
            "888",
            "758",
            "606",
            "751",
            "456",
            "794",
            "125",
            "511",
            "405",
            "614"
        ],
        "distance": 128.388671875,
        "computational_time": 221.064696
    },
    "batch_9": {
        "orders": [
            "2",
            "5",
            "92",
            "107",
            "142",
            "182",
            "188",
            "197",
            "224",
            "233",
            "269",
            "281",
            "284",
            "314",
            "323",
            "347",
            "398",
            "404",
            "419",
            "437",
            "440",
            "443",
            "458",
            "470",
            "494",
            "512",
            "545",
            "548"
        ],
        "pickRoute": [
            "1209",
            "866",
            "1257",
            "871",
            "1822",
            "2046",
            "817",
            "945",
            "1638",
            "218",
            "947",
            "859",
            "74",
            "1275",
            "812",
            "2080",
            "1867",
            "1367",
            "334",
            "1136",
            "1136",
            "697",
            "509",
            "1411",
            "338",
            "892",
            "2141",
            "1139",
            "2061",
            "1178",
            "1587",
            "207",
            "207",
            "568",
            "134",
            "1184",
            "240",
            "451",
            "1794",
            "299",
            "582",
            "1744",
            "1744",
            "1416"
        ],
        "SKUs": [
            "224",
            "223",
            "289",
            "489",
            "433",
            "522",
            "821",
            "9",
            "303",
            "141",
            "612",
            "662",
            "526",
            "667",
            "302",
            "663",
            "290",
            "748",
            "694",
            "428",
            "428",
            "281",
            "820",
            "774",
            "8",
            "604",
            "525",
            "345",
            "166",
            "825",
            "142",
            "4",
            "4",
            "718",
            "410",
            "476",
            "632",
            "710",
            "357",
            "672",
            "432",
            "611",
            "611",
            "488"
        ],
        "distance": 244.560546875,
        "computational_time": 222.046863
    },
    "batch_10": {
        "orders": [
            "26",
            "74",
            "89",
            "95",
            "98",
            "140",
            "175",
            "209",
            "212",
            "230",
            "236",
            "253",
            "257",
            "260",
            "290",
            "320",
            "353",
            "374",
            "416",
            "425",
            "436",
            "452",
            "464",
            "479",
            "482",
            "515",
            "569",
            "572"
        ],
        "pickRoute": [
            "1507",
            "1482",
            "520",
            "599",
            "390",
            "390",
            "1585",
            "1196",
            "1189",
            "292",
            "1201",
            "1211",
            "302",
            "1436",
            "440",
            "864",
            "1771",
            "1750",
            "708",
            "352",
            "1277",
            "372",
            "223",
            "2050",
            "2050",
            "2015",
            "165",
            "73",
            "1820",
            "733",
            "395",
            "603",
            "64",
            "1762",
            "694",
            "2112",
            "226",
            "1885",
            "1804",
            "1297",
            "238",
            "238",
            "1245",
            "1995",
            "184",
            "513",
            "565",
            "383",
            "2039",
            "1755",
            "798"
        ],
        "SKUs": [
            "269",
            "151",
            "729",
            "724",
            "534",
            "534",
            "113",
            "684",
            "41",
            "701",
            "627",
            "42",
            "443",
            "685",
            "529",
            "322",
            "391",
            "858",
            "533",
            "862",
            "728",
            "702",
            "112",
            "268",
            "268",
            "152",
            "396",
            "328",
            "147",
            "779",
            "221",
            "485",
            "135",
            "397",
            "626",
            "725",
            "857",
            "323",
            "360",
            "353",
            "660",
            "660",
            "642",
            "565",
            "861",
            "390",
            "136",
            "327",
            "641",
            "386",
            "661"
        ],
        "distance": 194.921875,
        "computational_time": 221.830263
    },
    "batch_11": {
        "orders": [
            "73",
            "76",
            "103",
            "118",
            "121",
            "181",
            "214",
            "226",
            "232",
            "247",
            "289",
            "304",
            "328",
            "361",
            "385",
            "415",
            "418",
            "460",
            "490",
            "493",
            "511",
            "520",
            "529",
            "535",
            "550",
            "571",
            "574",
            "586"
        ],
        "pickRoute": [
            "404",
            "237",
            "1570",
            "1801",
            "1700",
            "1005",
            "1237",
            "301",
            "2108",
            "485",
            "1035",
            "1157",
            "323",
            "662",
            "1384",
            "364",
            "1101",
            "239",
            "519",
            "1049",
            "633",
            "1959",
            "1036",
            "272",
            "1197",
            "1420",
            "410",
            "611",
            "833",
            "1659",
            "736",
            "872",
            "315",
            "162",
            "1602",
            "1880",
            "844",
            "851",
            "219",
            "1639",
            "750",
            "1907",
            "1918",
            "2087",
            "233",
            "399",
            "411",
            "2021",
            "1106",
            "105",
            "1888",
            "537",
            "899",
            "1241",
            "1586"
        ],
        "SKUs": [
            "860",
            "773",
            "356",
            "797",
            "785",
            "280",
            "747",
            "806",
            "740",
            "828",
            "183",
            "697",
            "110",
            "882",
            "497",
            "864",
            "348",
            "332",
            "461",
            "548",
            "188",
            "624",
            "630",
            "583",
            "279",
            "116",
            "441",
            "376",
            "158",
            "117",
            "678",
            "355",
            "582",
            "159",
            "772",
            "631",
            "675",
            "184",
            "798",
            "786",
            "498",
            "807",
            "128",
            "111",
            "187",
            "741",
            "347",
            "331",
            "460",
            "881",
            "442",
            "746",
            "625",
            "829",
            "377"
        ],
        "distance": 258.671875,
        "computational_time": 222.320739
    },
    "batch_12": {
        "orders": [
            "42",
            "43",
            "90",
            "117",
            "154",
            "165",
            "168",
            "195",
            "201",
            "207",
            "225",
            "282",
            "306",
            "315",
            "321",
            "351",
            "408",
            "426",
            "447",
            "450",
            "477",
            "528",
            "531",
            "534",
            "552",
            "555",
            "582",
            "591"
        ],
        "pickRoute": [
            "594",
            "1394",
            "1238",
            "847",
            "117",
            "2024",
            "1336",
            "1243",
            "492",
            "1726",
            "556",
            "1878",
            "2158",
            "1131",
            "197",
            "1373",
            "1439",
            "907",
            "1334",
            "1631",
            "883",
            "471",
            "2047",
            "347",
            "331",
            "331",
            "148",
            "1539",
            "922",
            "1712",
            "1577",
            "1627",
            "978",
            "92",
            "1840",
            "1396",
            "1693",
            "1975",
            "1798",
            "1607",
            "1508"
        ],
        "SKUs": [
            "239",
            "65",
            "310",
            "486",
            "319",
            "837",
            "260",
            "677",
            "346",
            "833",
            "875",
            "617",
            "722",
            "64",
            "300",
            "255",
            "430",
            "530",
            "318",
            "796",
            "477",
            "181",
            "643",
            "800",
            "463",
            "463",
            "805",
            "311",
            "681",
            "887",
            "137",
            "138",
            "182",
            "721",
            "867",
            "256",
            "682",
            "804",
            "832",
            "429",
            "717"
        ],
        "distance": 216.95703125,
        "computational_time": 220.780989
    },
    "batch_13": {
        "orders": [
            "24",
            "96",
            "105",
            "114",
            "132",
            "153",
            "180",
            "183",
            "192",
            "216",
            "219",
            "249",
            "261",
            "264",
            "279",
            "285",
            "303",
            "309",
            "327",
            "366",
            "390",
            "429",
            "465",
            "489",
            "498",
            "525",
            "537",
            "546"
        ],
        "pickRoute": [
            "137",
            "1721",
            "828",
            "93",
            "918",
            "1753",
            "1709",
            "815",
            "1741",
            "1459",
            "579",
            "1675",
            "1412",
            "1412",
            "832",
            "1838",
            "1562",
            "1583",
            "1492",
            "1766",
            "669",
            "1158",
            "103",
            "1609",
            "1250",
            "678",
            "1927",
            "311",
            "706",
            "1041",
            "756",
            "1576",
            "402",
            "984",
            "39",
            "1249",
            "1831",
            "1503",
            "1506",
            "400",
            "428",
            "320",
            "1785",
            "1852",
            "1422",
            "1823",
            "776",
            "1355"
        ],
        "SKUs": [
            "282",
            "278",
            "399",
            "296",
            "495",
            "554",
            "334",
            "425",
            "208",
            "381",
            "555",
            "703",
            "424",
            "424",
            "162",
            "163",
            "648",
            "39",
            "335",
            "649",
            "459",
            "339",
            "277",
            "238",
            "434",
            "468",
            "810",
            "176",
            "207",
            "592",
            "398",
            "177",
            "739",
            "823",
            "67",
            "591",
            "822",
            "738",
            "793",
            "754",
            "149",
            "404",
            "283",
            "148",
            "496",
            "295",
            "792",
            "380"
        ],
        "distance": 253.1640625,
        "computational_time": 221.648948
    },
    "batch_14": {
        "orders": [
            "7",
            "38",
            "56",
            "59",
            "71",
            "116",
            "147",
            "149",
            "185",
            "206",
            "211",
            "244",
            "248",
            "259",
            "286",
            "338",
            "340",
            "352",
            "380",
            "392",
            "439",
            "463",
            "506",
            "509",
            "519",
            "524",
            "539",
            "560"
        ],
        "pickRoute": [
            "314",
            "840",
            "916",
            "2130",
            "1314",
            "507",
            "489",
            "2137",
            "587",
            "1063",
            "189",
            "378",
            "75",
            "857",
            "1982",
            "2092",
            "382",
            "607",
            "52",
            "1514",
            "1454",
            "1359",
            "829",
            "1818",
            "1333",
            "1985",
            "1118",
            "1921",
            "807",
            "1905",
            "991",
            "432",
            "468",
            "774",
            "755",
            "935",
            "800",
            "1143",
            "1081",
            "1132",
            "1727",
            "937",
            "530",
            "1287"
        ],
        "SKUs": [
            "12",
            "531",
            "11",
            "326",
            "372",
            "515",
            "436",
            "394",
            "514",
            "665",
            "532",
            "325",
            "371",
            "784",
            "230",
            "769",
            "768",
            "575",
            "232",
            "764",
            "379",
            "512",
            "180",
            "178",
            "763",
            "317",
            "89",
            "790",
            "179",
            "108",
            "83",
            "791",
            "88",
            "845",
            "285",
            "594",
            "316",
            "59",
            "813",
            "378",
            "395",
            "666",
            "435",
            "700"
        ],
        "distance": 211.359375,
        "computational_time": 222.45534
    },
    "batch_15": {
        "orders": [
            "15",
            "39",
            "45",
            "57",
            "78",
            "87",
            "156",
            "159",
            "210",
            "237",
            "243",
            "246",
            "255",
            "262",
            "291",
            "294",
            "299",
            "375",
            "396",
            "399",
            "402",
            "435",
            "438",
            "457",
            "543",
            "567",
            "576",
            "588"
        ],
        "pickRoute": [
            "1793",
            "1772",
            "1931",
            "1931",
            "588",
            "1851",
            "867",
            "867",
            "116",
            "324",
            "818",
            "805",
            "1160",
            "1448",
            "1119",
            "583",
            "583",
            "1498",
            "619",
            "2004",
            "887",
            "1154",
            "1777",
            "2113",
            "1198",
            "1344",
            "1053",
            "881",
            "1195",
            "1833",
            "1263",
            "66",
            "560",
            "1858",
            "300",
            "441",
            "1261",
            "906",
            "1258",
            "1386",
            "450",
            "1881",
            "160",
            "1423",
            "1220"
        ],
        "SKUs": [
            "401",
            "692",
            "124",
            "124",
            "68",
            "84",
            "245",
            "245",
            "454",
            "120",
            "567",
            "61",
            "25",
            "60",
            "664",
            "866",
            "866",
            "85",
            "609",
            "69",
            "855",
            "132",
            "370",
            "447",
            "659",
            "600",
            "361",
            "388",
            "817",
            "884",
            "444",
            "375",
            "324",
            "133",
            "658",
            "246",
            "73",
            "566",
            "601",
            "242",
            "374",
            "605",
            "308",
            "400",
            "693"
        ],
        "distance": 239.623046875,
        "computational_time": 222.123356
    },
    "batch_16": {
        "orders": [
            "17",
            "80",
            "110",
            "122",
            "143",
            "158",
            "170",
            "173",
            "200",
            "203",
            "227",
            "272",
            "305",
            "308",
            "332",
            "350",
            "362",
            "401",
            "431",
            "449",
            "485",
            "488",
            "491",
            "497",
            "500",
            "575",
            "578",
            "593"
        ],
        "pickRoute": [
            "2073",
            "1387",
            "2060",
            "1278",
            "15",
            "1674",
            "371",
            "160",
            "790",
            "1208",
            "1212",
            "1656",
            "503",
            "1052",
            "2111",
            "380",
            "1289",
            "484",
            "1504",
            "464",
            "2131",
            "440",
            "1217",
            "1190",
            "1016",
            "1636",
            "2143",
            "2143",
            "1339",
            "1210",
            "1393",
            "1835",
            "1058",
            "1850",
            "1579",
            "153",
            "1945",
            "1338",
            "416",
            "1708"
        ],
        "SKUs": [
            "737",
            "122",
            "189",
            "349",
            "466",
            "28",
            "350",
            "308",
            "680",
            "732",
            "889",
            "190",
            "170",
            "743",
            "244",
            "869",
            "742",
            "652",
            "462",
            "413",
            "607",
            "529",
            "313",
            "309",
            "549",
            "505",
            "123",
            "123",
            "865",
            "262",
            "756",
            "736",
            "504",
            "225",
            "467",
            "868",
            "753",
            "608",
            "752",
            "266"
        ],
        "distance": 174.81640625,
        "computational_time": 222.249771
    },
    "batch_17": {
        "orders": [
            "11",
            "14",
            "23",
            "32",
            "35",
            "125",
            "161",
            "167",
            "191",
            "215",
            "242",
            "263",
            "275",
            "278",
            "317",
            "335",
            "344",
            "356",
            "359",
            "365",
            "371",
            "395",
            "410",
            "434",
            "476",
            "503",
            "527",
            "536"
        ],
        "pickRoute": [
            "181",
            "107",
            "107",
            "1678",
            "1698",
            "655",
            "108",
            "877",
            "36",
            "313",
            "448",
            "159",
            "1603",
            "89",
            "71",
            "394",
            "1495",
            "1682",
            "270",
            "1633",
            "1558",
            "287",
            "1582",
            "1358",
            "111",
            "1268",
            "2059",
            "1402",
            "286",
            "1251",
            "987",
            "84",
            "944",
            "944",
            "1458",
            "474",
            "1319",
            "911",
            "1148",
            "1443",
            "1380",
            "952",
            "125",
            "1550",
            "1550",
            "1456",
            "1478",
            "705",
            "1381",
            "276",
            "253",
            "1004",
            "1680"
        ],
        "SKUs": [
            "552",
            "418",
            "418",
            "402",
            "259",
            "55",
            "18",
            "509",
            "333",
            "294",
            "480",
            "37",
            "656",
            "544",
            "759",
            "50",
            "368",
            "619",
            "423",
            "809",
            "24",
            "599",
            "23",
            "720",
            "195",
            "51",
            "19",
            "422",
            "508",
            "369",
            "479",
            "521",
            "520",
            "520",
            "657",
            "560",
            "538",
            "258",
            "808",
            "56",
            "539",
            "719",
            "553",
            "248",
            "248",
            "795",
            "561",
            "403",
            "38",
            "598",
            "249",
            "545",
            "196"
        ],
        "distance": 220.869140625,
        "computational_time": 220.985245
    },
    "batch_18": {
        "orders": [
            "13",
            "28",
            "47",
            "79",
            "85",
            "112",
            "130",
            "145",
            "163",
            "172",
            "193",
            "229",
            "238",
            "250",
            "316",
            "341",
            "349",
            "364",
            "373",
            "376",
            "388",
            "445",
            "499",
            "517",
            "568",
            "580",
            "583",
            "595"
        ],
        "pickRoute": [
            "1429",
            "236",
            "1388",
            "176",
            "821",
            "251",
            "456",
            "844",
            "265",
            "1364",
            "54",
            "2147",
            "1538",
            "1342",
            "724",
            "870",
            "2168",
            "139",
            "119",
            "1925",
            "426",
            "732",
            "421",
            "1928",
            "2084",
            "2075",
            "1828",
            "1911",
            "2017",
            "890",
            "1616",
            "1213",
            "1410",
            "1754"
        ],
        "SKUs": [
            "872",
            "297",
            "22",
            "893",
            "528",
            "21",
            "252",
            "675",
            "362",
            "44",
            "588",
            "876",
            "568",
            "478",
            "782",
            "205",
            "352",
            "877",
            "755",
            "564",
            "572",
            "551",
            "71",
            "516",
            "382",
            "129",
            "121",
            "265",
            "173",
            "856",
            "228",
            "363",
            "892",
            "569"
        ],
        "distance": 198.13671875,
        "computational_time": 221.155278
    },
    "batch_19": {
        "orders": [
            "29",
            "41",
            "50",
            "53",
            "65",
            "86",
            "101",
            "113",
            "131",
            "137",
            "251",
            "293",
            "296",
            "302",
            "311",
            "389",
            "407",
            "413",
            "422",
            "467",
            "518",
            "530",
            "533",
            "563",
            "566",
            "581",
            "584",
            "587"
        ],
        "pickRoute": [
            "275",
            "824",
            "1891",
            "290",
            "1875",
            "1763",
            "1391",
            "693",
            "392",
            "1042",
            "645",
            "1702",
            "2127",
            "2127",
            "1417",
            "402",
            "1844",
            "1363",
            "1873",
            "1228",
            "2008",
            "1415",
            "1294",
            "1670",
            "822",
            "1431",
            "929",
            "1464",
            "1057",
            "700",
            "1374",
            "964",
            "1941",
            "1816",
            "1193",
            "1953",
            "954",
            "298",
            "748",
            "683",
            "1413",
            "100",
            "255",
            "1488",
            "1471",
            "473"
        ],
        "SKUs": [
            "45",
            "174",
            "803",
            "99",
            "854",
            "216",
            "615",
            "206",
            "706",
            "131",
            "783",
            "100",
            "63",
            "63",
            "74",
            "739",
            "384",
            "879",
            "472",
            "130",
            "883",
            "217",
            "616",
            "458",
            "77",
            "873",
            "622",
            "446",
            "450",
            "156",
            "849",
            "802",
            "799",
            "175",
            "636",
            "457",
            "590",
            "853",
            "383",
            "78",
            "874",
            "449",
            "878",
            "637",
            "589",
            "471"
        ],
        "distance": 222.912109375,
        "computational_time": 221.928739
    },
    "batch_20": {
        "orders": [
            "1",
            "4",
            "52",
            "70",
            "94",
            "109",
            "124",
            "136",
            "152",
            "160",
            "187",
            "199",
            "268",
            "274",
            "280",
            "307",
            "319",
            "331",
            "343",
            "369",
            "379",
            "382",
            "430",
            "442",
            "466",
            "514",
            "544",
            "559"
        ],
        "pickRoute": [
            "988",
            "11",
            "966",
            "990",
            "151",
            "1000",
            "1088",
            "1231",
            "1661",
            "1848",
            "716",
            "896",
            "2118",
            "229",
            "2040",
            "1141",
            "2081",
            "524",
            "1346",
            "605",
            "605",
            "666",
            "1102",
            "1140",
            "1485",
            "879",
            "1120",
            "1545",
            "521",
            "1291",
            "245",
            "1389",
            "1553",
            "673",
            "1489",
            "1817",
            "1355",
            "1751",
            "499",
            "1075",
            "948",
            "2164",
            "536",
            "375",
            "528",
            "532",
            "888",
            "2025",
            "1307",
            "449",
            "1811",
            "830",
            "1390",
            "171",
            "23"
        ],
        "SKUs": [
            "818",
            "409",
            "288",
            "76",
            "7",
            "247",
            "670",
            "671",
            "307",
            "819",
            "3",
            "214",
            "2",
            "416",
            "778",
            "169",
            "844",
            "426",
            "106",
            "574",
            "574",
            "168",
            "306",
            "483",
            "6",
            "417",
            "194",
            "651",
            "30",
            "464",
            "145",
            "193",
            "465",
            "231",
            "427",
            "558",
            "380",
            "650",
            "705",
            "519",
            "146",
            "573",
            "107",
            "215",
            "502",
            "237",
            "578",
            "287",
            "484",
            "503",
            "408",
            "704",
            "843",
            "777",
            "577"
        ],
        "distance": 250.375,
        "computational_time": 222.402334
    },
    "batch_21": {
        "orders": [
            "10",
            "19",
            "25",
            "34",
            "37",
            "61",
            "106",
            "115",
            "134",
            "146",
            "178",
            "208",
            "217",
            "254",
            "256",
            "271",
            "313",
            "325",
            "326",
            "346",
            "358",
            "421",
            "424",
            "505",
            "542",
            "556",
            "565",
            "589"
        ],
        "pickRoute": [
            "1797",
            "956",
            "1354",
            "209",
            "1192",
            "1743",
            "962",
            "360",
            "1933",
            "1007",
            "1274",
            "1500",
            "1890",
            "191",
            "521",
            "1376",
            "933",
            "1590",
            "1876",
            "444",
            "341",
            "1981",
            "80",
            "950",
            "744",
            "123",
            "1818",
            "212",
            "459",
            "1669",
            "1887",
            "158",
            "1615",
            "2123",
            "1705",
            "898",
            "368",
            "50",
            "460",
            "70",
            "144",
            "1834"
        ],
        "SKUs": [
            "321",
            "640",
            "475",
            "389",
            "635",
            "58",
            "885",
            "523",
            "412",
            "493",
            "839",
            "54",
            "92",
            "40",
            "30",
            "275",
            "543",
            "851",
            "542",
            "165",
            "405",
            "761",
            "93",
            "31",
            "634",
            "852",
            "178",
            "492",
            "164",
            "320",
            "336",
            "16",
            "838",
            "211",
            "816",
            "229",
            "494",
            "387",
            "274",
            "524",
            "17",
            "762"
        ],
        "distance": 211.849609375,
        "computational_time": 221.559092
    },
    "batch_22": {
        "orders": [
            "27",
            "31",
            "33",
            "58",
            "63",
            "66",
            "68",
            "123",
            "126",
            "129",
            "177",
            "202",
            "213",
            "222",
            "267",
            "273",
            "300",
            "372",
            "393",
            "417",
            "423",
            "459",
            "474",
            "501",
            "510",
            "570",
            "579",
            "594"
        ],
        "pickRoute": [
            "1099",
            "1800",
            "13",
            "1460",
            "1671",
            "1285",
            "1233",
            "365",
            "1926",
            "1926",
            "1740",
            "1740",
            "2089",
            "1630",
            "374",
            "783",
            "1808",
            "1748",
            "9",
            "995",
            "1077",
            "2133",
            "1266",
            "495",
            "1547",
            "10",
            "1694",
            "1694",
            "210",
            "1736",
            "1114",
            "2054",
            "2085",
            "923",
            "2011",
            "1221",
            "437",
            "284",
            "284",
            "869",
            "576",
            "547",
            "505",
            "1847",
            "1646",
            "676",
            "2041",
            "1523",
            "1856",
            "972",
            "2076",
            "903",
            "1366",
            "657",
            "1110",
            "941"
        ],
        "SKUs": [
            "48",
            "312",
            "757",
            "628",
            "638",
            "455",
            "340",
            "407",
            "770",
            "770",
            "197",
            "197",
            "716",
            "595",
            "191",
            "562",
            "53",
            "414",
            "198",
            "563",
            "695",
            "52",
            "343",
            "859",
            "204",
            "715",
            "890",
            "890",
            "415",
            "771",
            "96",
            "452",
            "329",
            "870",
            "596",
            "273",
            "43",
            "104",
            "104",
            "101",
            "192",
            "629",
            "891",
            "871",
            "105",
            "203",
            "330",
            "696",
            "490",
            "639",
            "272",
            "97",
            "342",
            "87",
            "49",
            "86"
        ],
        "distance": 272.123046875,
        "computational_time": 221.266797
    }
}