{
    "batch_1": {
        "orders": [
            "74",
            "102",
            "104",
            "110",
            "122",
            "158",
            "191",
            "201",
            "209",
            "246",
            "276",
            "300",
            "305",
            "314",
            "329",
            "405",
            "443",
            "450"
        ],
        "pickRoute": [
            "1333",
            "1864",
            "2134",
            "1216",
            "393",
            "572",
            "479",
            "1942",
            "696",
            "1455",
            "1820",
            "73",
            "165",
            "564",
            "1212",
            "501",
            "909",
            "1915",
            "607",
            "1965",
            "1361",
            "1451",
            "2012",
            "1474",
            "760",
            "1336",
            "1817",
            "1432",
            "883",
            "1646",
            "454",
            "478",
            "1276",
            "1366",
            "1607",
            "777",
            "1798",
            "1151",
            "1588",
            "1155",
            "218",
            "911",
            "1550",
            "1143",
            "1055"
        ],
        "SKUs": [
            "323",
            "248",
            "211",
            "249",
            "383",
            "224",
            "909",
            "427",
            "676",
            "677",
            "144",
            "210",
            "143",
            "250",
            "145",
            "911",
            "649",
            "322",
            "225",
            "632",
            "212",
            "425",
            "910",
            "407",
            "925",
            "502",
            "621",
            "620",
            "571",
            "830",
            "829",
            "408",
            "622",
            "206",
            "207",
            "503",
            "927",
            "926",
            "570",
            "633",
            "648",
            "384",
            "426",
            "678",
            "385"
        ],
        "distance": 298.8359375,
        "computational_time": 251.146142
    },
    "batch_2": {
        "orders": [
            "60",
            "69",
            "75",
            "81",
            "96",
            "123",
            "138",
            "150",
            "159",
            "168",
            "213",
            "216",
            "219",
            "249",
            "261",
            "297",
            "306",
            "318",
            "339",
            "342",
            "381",
            "387",
            "408",
            "486",
            "489"
        ],
        "pickRoute": [
            "1089",
            "581",
            "644",
            "1238",
            "650",
            "1976",
            "642",
            "2142",
            "1852",
            "1631",
            "1302",
            "1823",
            "1422",
            "1037",
            "400",
            "428",
            "31",
            "1311",
            "706",
            "311",
            "2102",
            "592",
            "1609",
            "116",
            "194",
            "422",
            "1053",
            "881",
            "925",
            "756",
            "635",
            "1248",
            "1831",
            "856",
            "1041",
            "1491",
            "1503",
            "472",
            "1524",
            "1239",
            "1978",
            "419",
            "213",
            "2064",
            "1013",
            "1936",
            "728",
            "303",
            "1356",
            "266",
            "951",
            "682",
            "1350",
            "1282",
            "197",
            "1472",
            "1273"
        ],
        "SKUs": [
            "792",
            "445",
            "836",
            "779",
            "148",
            "536",
            "698",
            "994",
            "835",
            "510",
            "697",
            "251",
            "146",
            "509",
            "780",
            "434",
            "120",
            "135",
            "634",
            "439",
            "699",
            "793",
            "304",
            "837",
            "325",
            "121",
            "433",
            "164",
            "163",
            "340",
            "192",
            "446",
            "655",
            "538",
            "191",
            "614",
            "281",
            "324",
            "704",
            "1000",
            "705",
            "656",
            "993",
            "654",
            "999",
            "252",
            "613",
            "119",
            "162",
            "341",
            "537",
            "303",
            "805",
            "511",
            "147",
            "339",
            "326"
        ],
        "distance": 256.216796875,
        "computational_time": 249.209901
    },
    "batch_3": {
        "orders": [
            "49",
            "55",
            "88",
            "94",
            "115",
            "133",
            "184",
            "187",
            "196",
            "199",
            "208",
            "211",
            "229",
            "232",
            "235",
            "253",
            "256",
            "271",
            "280",
            "286",
            "343",
            "349",
            "355",
            "442",
            "484"
        ],
        "pickRoute": [
            "87",
            "1087",
            "1781",
            "1860",
            "2036",
            "1948",
            "1231",
            "410",
            "1121",
            "962",
            "609",
            "1288",
            "896",
            "1710",
            "1737",
            "146",
            "2157",
            "1538",
            "1185",
            "554",
            "521",
            "191",
            "1537",
            "1782",
            "477",
            "1362",
            "2032",
            "1590",
            "2152",
            "1611",
            "2138",
            "848",
            "1841",
            "865",
            "193",
            "1669",
            "163",
            "1731",
            "1241",
            "919"
        ],
        "SKUs": [
            "269",
            "188",
            "374",
            "477",
            "716",
            "706",
            "908",
            "403",
            "236",
            "578",
            "107",
            "431",
            "476",
            "471",
            "177",
            "424",
            "519",
            "396",
            "729",
            "990",
            "526",
            "556",
            "991",
            "525",
            "189",
            "270",
            "592",
            "234",
            "717",
            "271",
            "235",
            "557",
            "579",
            "108",
            "465",
            "95",
            "593",
            "378",
            "373",
            "430"
        ],
        "distance": 174.8515625,
        "computational_time": 249.296596
    },
    "batch_4": {
        "orders": [
            "4",
            "11",
            "35",
            "44",
            "56",
            "140",
            "179",
            "182",
            "200",
            "203",
            "239",
            "242",
            "248",
            "266",
            "272",
            "284",
            "326",
            "347",
            "365",
            "380",
            "410",
            "437",
            "452",
            "455",
            "479"
        ],
        "pickRoute": [
            "879",
            "1596",
            "2073",
            "1359",
            "863",
            "433",
            "349",
            "1318",
            "954",
            "503",
            "523",
            "1614",
            "1914",
            "1379",
            "1339",
            "2143",
            "474",
            "2050",
            "733",
            "1499",
            "1297",
            "238",
            "1104",
            "129",
            "1275",
            "1862",
            "1579",
            "1306",
            "386",
            "1312",
            "234",
            "691",
            "691",
            "1446",
            "917",
            "1867",
            "2080",
            "513",
            "812",
            "876",
            "1148",
            "2165",
            "122",
            "2112",
            "2112",
            "694",
            "1674",
            "655",
            "800",
            "1093",
            "1839",
            "977",
            "1067",
            "1132",
            "1513",
            "1501",
            "1792",
            "325",
            "1541",
            "483",
            "1899",
            "562"
        ],
        "SKUs": [
            "652",
            "7",
            "939",
            "937",
            "87",
            "411",
            "560",
            "508",
            "842",
            "110",
            "486",
            "898",
            "558",
            "364",
            "109",
            "778",
            "413",
            "406",
            "984",
            "747",
            "983",
            "67",
            "111",
            "405",
            "487",
            "365",
            "559",
            "713",
            "932",
            "507",
            "546",
            "285",
            "285",
            "404",
            "18",
            "670",
            "841",
            "88",
            "412",
            "938",
            "985",
            "590",
            "897",
            "8",
            "8",
            "371",
            "369",
            "588",
            "363",
            "17",
            "68",
            "589",
            "899",
            "547",
            "548",
            "132",
            "776",
            "777",
            "931",
            "494",
            "748",
            "370"
        ],
        "distance": 238.044921875,
        "computational_time": 249.399396
    },
    "batch_5": {
        "orders": [
            "19",
            "40",
            "73",
            "79",
            "85",
            "124",
            "139",
            "151",
            "175",
            "178",
            "205",
            "250",
            "268",
            "289",
            "328",
            "337",
            "371",
            "397",
            "403",
            "424",
            "449",
            "460",
            "463",
            "469",
            "490"
        ],
        "pickRoute": [
            "1837",
            "1134",
            "1845",
            "301",
            "1035",
            "1157",
            "974",
            "1600",
            "418",
            "1070",
            "630",
            "850",
            "2117",
            "1197",
            "192",
            "1684",
            "1034",
            "1967",
            "1044",
            "1876",
            "1811",
            "1096",
            "1854",
            "1113",
            "1658",
            "739",
            "950",
            "1324",
            "1904",
            "212",
            "1807",
            "443",
            "265",
            "1129",
            "840",
            "671",
            "829",
            "1791",
            "510",
            "264",
            "455",
            "75",
            "734",
            "1357",
            "1142",
            "1023",
            "2101",
            "1342",
            "494",
            "1907",
            "656",
            "1827",
            "1238",
            "547",
            "2018",
            "1592",
            "991",
            "1438",
            "351",
            "1919",
            "2037",
            "1287",
            "530",
            "1187",
            "537",
            "802",
            "1435"
        ],
        "SKUs": [
            "284",
            "810",
            "156",
            "513",
            "695",
            "967",
            "282",
            "551",
            "811",
            "142",
            "1002",
            "157",
            "354",
            "253",
            "418",
            "36",
            "812",
            "956",
            "306",
            "78",
            "951",
            "172",
            "512",
            "1003",
            "865",
            "361",
            "283",
            "158",
            "174",
            "305",
            "355",
            "79",
            "552",
            "35",
            "514",
            "254",
            "924",
            "758",
            "694",
            "966",
            "950",
            "419",
            "866",
            "826",
            "80",
            "141",
            "675",
            "173",
            "824",
            "597",
            "825",
            "598",
            "779",
            "744",
            "176",
            "759",
            "922",
            "362",
            "923",
            "307",
            "34",
            "674",
            "1001",
            "673",
            "417",
            "356",
            "968"
        ],
        "distance": 320.02734375,
        "computational_time": 250.963157
    },
    "batch_6": {
        "orders": [
            "3",
            "6",
            "9",
            "42",
            "45",
            "87",
            "108",
            "144",
            "146",
            "156",
            "198",
            "220",
            "225",
            "228",
            "231",
            "234",
            "243",
            "309",
            "321",
            "348",
            "384",
            "393",
            "416",
            "453",
            "492"
        ],
        "pickRoute": [
            "1450",
            "736",
            "847",
            "117",
            "1097",
            "21",
            "1525",
            "195",
            "1962",
            "1161",
            "41",
            "1655",
            "1672",
            "867",
            "998",
            "1562",
            "326",
            "326",
            "1833",
            "224",
            "904",
            "1779",
            "1180",
            "1724",
            "1938",
            "1733",
            "745",
            "875",
            "1260",
            "1229",
            "639",
            "639",
            "634",
            "1056",
            "1901",
            "1901",
            "402",
            "2103",
            "246",
            "1978",
            "1303",
            "1396",
            "1315",
            "1673",
            "2018",
            "1693",
            "1467",
            "913",
            "994",
            "307",
            "1004",
            "826",
            "548"
        ],
        "SKUs": [
            "448",
            "447",
            "400",
            "6",
            "715",
            "11",
            "90",
            "454",
            "1007",
            "83",
            "469",
            "456",
            "464",
            "402",
            "495",
            "787",
            "297",
            "297",
            "933",
            "401",
            "474",
            "463",
            "91",
            "5",
            "10",
            "89",
            "475",
            "222",
            "1006",
            "470",
            "84",
            "84",
            "292",
            "455",
            "14",
            "14",
            "662",
            "804",
            "496",
            "705",
            "637",
            "714",
            "82",
            "317",
            "176",
            "263",
            "318",
            "296",
            "298",
            "850",
            "851",
            "852",
            "449"
        ],
        "distance": 290.140625,
        "computational_time": 249.589434
    },
    "batch_7": {
        "orders": [
            "15",
            "43",
            "58",
            "90",
            "93",
            "112",
            "118",
            "127",
            "147",
            "162",
            "189",
            "190",
            "192",
            "238",
            "324",
            "334",
            "345",
            "415",
            "420",
            "444",
            "448",
            "465",
            "472",
            "477",
            "478"
        ],
        "pickRoute": [
            "666",
            "550",
            "236",
            "162",
            "119",
            "1532",
            "616",
            "622",
            "624",
            "1331",
            "2058",
            "1878",
            "2158",
            "584",
            "960",
            "1205",
            "269",
            "1982",
            "1355",
            "33",
            "1385",
            "587",
            "750",
            "2130",
            "811",
            "189",
            "2087",
            "732",
            "233",
            "843",
            "851",
            "1880",
            "57",
            "1220",
            "983",
            "1301",
            "912",
            "1453"
        ],
        "SKUs": [
            "974",
            "921",
            "982",
            "116",
            "848",
            "242",
            "484",
            "25",
            "912",
            "709",
            "980",
            "180",
            "299",
            "330",
            "858",
            "667",
            "386",
            "958",
            "380",
            "187",
            "230",
            "85",
            "981",
            "381",
            "920",
            "228",
            "483",
            "688",
            "849",
            "258",
            "382",
            "973",
            "259",
            "241",
            "86",
            "229",
            "115",
            "485"
        ],
        "distance": 175.126953125,
        "computational_time": 249.652857
    },
    "batch_8": {
        "orders": [
            "2",
            "5",
            "16",
            "38",
            "41",
            "62",
            "67",
            "82",
            "86",
            "103",
            "161",
            "217",
            "221",
            "224",
            "278",
            "304",
            "313",
            "317",
            "320",
            "352",
            "419",
            "430",
            "457",
            "464",
            "482"
        ],
        "pickRoute": [
            "404",
            "835",
            "182",
            "1570",
            "2097",
            "1102",
            "1797",
            "1347",
            "1426",
            "2081",
            "1049",
            "1601",
            "1821",
            "1717",
            "51",
            "110",
            "431",
            "2034",
            "144",
            "416",
            "1585",
            "1832",
            "668",
            "292",
            "1666",
            "1223",
            "991",
            "1124",
            "47",
            "2",
            "868",
            "2061",
            "2077",
            "1271",
            "1501",
            "1747",
            "1177",
            "1328",
            "1174"
        ],
        "SKUs": [
            "631",
            "28",
            "26",
            "165",
            "27",
            "882",
            "441",
            "646",
            "630",
            "943",
            "167",
            "442",
            "209",
            "647",
            "883",
            "166",
            "208",
            "440",
            "944",
            "661",
            "125",
            "653",
            "81",
            "329",
            "4",
            "988",
            "922",
            "660",
            "857",
            "957",
            "574",
            "453",
            "9",
            "75",
            "132",
            "723",
            "450",
            "175",
            "3"
        ],
        "distance": 206.54296875,
        "computational_time": 249.911178
    },
    "batch_9": {
        "orders": [
            "8",
            "13",
            "22",
            "29",
            "50",
            "64",
            "70",
            "72",
            "106",
            "160",
            "176",
            "212",
            "214",
            "259",
            "263",
            "307",
            "308",
            "323",
            "340",
            "356",
            "358",
            "406",
            "413",
            "475",
            "476"
        ],
        "pickRoute": [
            "1000",
            "1505",
            "649",
            "373",
            "1729",
            "2096",
            "631",
            "140",
            "1800",
            "833",
            "872",
            "1574",
            "200",
            "1639",
            "673",
            "2126",
            "1742",
            "1514",
            "52",
            "599",
            "807",
            "2069",
            "383",
            "250",
            "1905",
            "834",
            "270",
            "1985",
            "727",
            "399",
            "888",
            "135",
            "466",
            "353"
        ],
        "SKUs": [
            "216",
            "136",
            "701",
            "328",
            "832",
            "43",
            "977",
            "532",
            "700",
            "533",
            "218",
            "635",
            "140",
            "21",
            "831",
            "128",
            "733",
            "846",
            "730",
            "666",
            "96",
            "54",
            "13",
            "636",
            "979",
            "542",
            "432",
            "435",
            "137",
            "327",
            "217",
            "978",
            "42",
            "357"
        ],
        "distance": 189.150390625,
        "computational_time": 249.467485
    },
    "batch_10": {
        "orders": [
            "12",
            "24",
            "33",
            "54",
            "63",
            "120",
            "126",
            "141",
            "165",
            "171",
            "180",
            "186",
            "222",
            "267",
            "270",
            "291",
            "315",
            "354",
            "367",
            "399",
            "402",
            "426",
            "438",
            "462",
            "483"
        ],
        "pickRoute": [
            "1410",
            "1419",
            "1080",
            "1577",
            "1671",
            "1233",
            "137",
            "1074",
            "331",
            "471",
            "59",
            "1694",
            "442",
            "1695",
            "553",
            "1851",
            "1703",
            "1530",
            "638",
            "2027",
            "391",
            "1569",
            "29",
            "975",
            "1300",
            "805",
            "761",
            "1637",
            "1635",
            "2004",
            "3",
            "241",
            "1777",
            "16",
            "676",
            "42",
            "1397",
            "406",
            "202",
            "1604",
            "458",
            "1334",
            "1152",
            "1131",
            "199"
        ],
        "SKUs": [
            "751",
            "727",
            "554",
            "344",
            "336",
            "20",
            "244",
            "817",
            "871",
            "256",
            "257",
            "352",
            "345",
            "650",
            "954",
            "451",
            "106",
            "651",
            "601",
            "728",
            "105",
            "872",
            "127",
            "286",
            "126",
            "63",
            "989",
            "46",
            "47",
            "366",
            "377",
            "823",
            "549",
            "555",
            "816",
            "19",
            "367",
            "288",
            "900",
            "870",
            "335",
            "550",
            "955",
            "62",
            "287"
        ],
        "distance": 256.01171875,
        "computational_time": 250.066048
    },
    "batch_11": {
        "orders": [
            "37",
            "52",
            "61",
            "76",
            "91",
            "97",
            "121",
            "130",
            "145",
            "202",
            "244",
            "274",
            "277",
            "298",
            "319",
            "322",
            "331",
            "346",
            "364",
            "382",
            "400",
            "433",
            "436",
            "439",
            "451"
        ],
        "pickRoute": [
            "667",
            "362",
            "1510",
            "2136",
            "1728",
            "436",
            "1790",
            "1368",
            "25",
            "813",
            "170",
            "1098",
            "1760",
            "735",
            "1005",
            "601",
            "1064",
            "1295",
            "1200",
            "1337",
            "1793",
            "1548",
            "487",
            "272",
            "1079",
            "1254",
            "1414",
            "1500",
            "1890",
            "306",
            "1683",
            "1376",
            "245",
            "251",
            "456",
            "823",
            "219",
            "56",
            "542",
            "1553",
            "65",
            "1314",
            "1137",
            "1752",
            "366",
            "2137",
            "511",
            "308",
            "1676",
            "339",
            "767",
            "751",
            "1665",
            "1932",
            "703",
            "499",
            "62",
            "1202",
            "2020",
            "216",
            "1970",
            "1621",
            "1084",
            "411",
            "744",
            "986",
            "1696",
            "1551",
            "1699",
            "244",
            "1908",
            "171",
            "899"
        ],
        "SKUs": [
            "746",
            "264",
            "889",
            "658",
            "663",
            "73",
            "711",
            "573",
            "194",
            "409",
            "181",
            "901",
            "928",
            "122",
            "615",
            "564",
            "150",
            "684",
            "894",
            "497",
            "818",
            "183",
            "902",
            "683",
            "566",
            "565",
            "102",
            "820",
            "295",
            "783",
            "101",
            "665",
            "124",
            "74",
            "781",
            "929",
            "617",
            "819",
            "682",
            "247",
            "410",
            "712",
            "72",
            "888",
            "903",
            "182",
            "572",
            "659",
            "151",
            "887",
            "895",
            "782",
            "498",
            "657",
            "294",
            "123",
            "668",
            "745",
            "896",
            "246",
            "884",
            "100",
            "195",
            "193",
            "616",
            "664",
            "266",
            "265",
            "245",
            "930",
            "293",
            "710",
            "149"
        ],
        "distance": 259.05859375,
        "computational_time": 250.147211
    },
    "batch_12": {
        "orders": [
            "71",
            "92",
            "113",
            "149",
            "154",
            "164",
            "173",
            "185",
            "218",
            "227",
            "257",
            "275",
            "281",
            "287",
            "311",
            "341",
            "344",
            "368",
            "389",
            "392",
            "407",
            "422",
            "428",
            "431",
            "491"
        ],
        "pickRoute": [
            "1755",
            "1526",
            "534",
            "1081",
            "764",
            "1416",
            "774",
            "2039",
            "277",
            "1970",
            "415",
            "403",
            "228",
            "1633",
            "2154",
            "957",
            "397",
            "1483",
            "1208",
            "688",
            "38",
            "929",
            "1072",
            "121",
            "822",
            "1294",
            "1750",
            "964",
            "1193",
            "1849",
            "719",
            "102",
            "138",
            "334",
            "1685",
            "1411",
            "338",
            "892",
            "701",
            "680",
            "473",
            "1805",
            "1108",
            "641",
            "1541",
            "1164",
            "1178",
            "752",
            "1320",
            "1784",
            "1335",
            "1317",
            "1172",
            "1980",
            "429",
            "765",
            "1747",
            "1680"
        ],
        "SKUs": [
            "313",
            "877",
            "333",
            "139",
            "568",
            "581",
            "862",
            "834",
            "795",
            "884",
            "803",
            "350",
            "528",
            "833",
            "752",
            "351",
            "796",
            "580",
            "460",
            "1005",
            "702",
            "334",
            "462",
            "878",
            "443",
            "708",
            "186",
            "302",
            "376",
            "641",
            "232",
            "861",
            "529",
            "301",
            "567",
            "527",
            "885",
            "642",
            "185",
            "138",
            "444",
            "594",
            "797",
            "375",
            "931",
            "876",
            "184",
            "707",
            "753",
            "231",
            "461",
            "1004",
            "332",
            "703",
            "860",
            "349",
            "723",
            "569"
        ],
        "distance": 231.162109375,
        "computational_time": 251.083313
    },
    "batch_13": {
        "orders": [
            "14",
            "65",
            "68",
            "77",
            "80",
            "83",
            "95",
            "101",
            "125",
            "143",
            "155",
            "167",
            "197",
            "230",
            "233",
            "245",
            "269",
            "290",
            "293",
            "335",
            "374",
            "383",
            "401",
            "425",
            "470"
        ],
        "pickRoute": [
            "294",
            "882",
            "1622",
            "1917",
            "1009",
            "1058",
            "2115",
            "395",
            "1033",
            "1713",
            "153",
            "255",
            "2090",
            "240",
            "134",
            "149",
            "30",
            "1861",
            "63",
            "468",
            "697",
            "509",
            "276",
            "1991",
            "1471",
            "2026",
            "207",
            "1083",
            "496",
            "1048",
            "2105",
            "1868",
            "1218",
            "570",
            "1425",
            "2007",
            "1179",
            "2030",
            "1427",
            "1595",
            "1533",
            "1149",
            "606",
            "625",
            "997",
            "1977",
            "935",
            "2000",
            "1380",
            "500",
            "873",
            "421",
            "111",
            "1117",
            "602"
        ],
        "SKUs": [
            "691",
            "784",
            "786",
            "689",
            "134",
            "129",
            "160",
            "22",
            "316",
            "203",
            "600",
            "499",
            "24",
            "599",
            "821",
            "467",
            "397",
            "472",
            "204",
            "553",
            "500",
            "466",
            "314",
            "473",
            "971",
            "205",
            "133",
            "605",
            "190",
            "291",
            "970",
            "764",
            "785",
            "161",
            "969",
            "130",
            "255",
            "152",
            "338",
            "159",
            "501",
            "606",
            "868",
            "690",
            "169",
            "468",
            "23",
            "822",
            "867",
            "168",
            "869",
            "399",
            "398",
            "315",
            "290"
        ],
        "distance": 239.94140625,
        "computational_time": 248.990917
    },
    "batch_14": {
        "orders": [
            "47",
            "48",
            "53",
            "59",
            "116",
            "119",
            "137",
            "170",
            "183",
            "188",
            "194",
            "206",
            "236",
            "251",
            "254",
            "296",
            "333",
            "377",
            "394",
            "404",
            "434",
            "461",
            "473",
            "485",
            "488"
        ],
        "pickRoute": [
            "1985",
            "2060",
            "1146",
            "1118",
            "1169",
            "824",
            "1257",
            "2092",
            "1949",
            "1763",
            "186",
            "1350",
            "1975",
            "1789",
            "2008",
            "1188",
            "1057",
            "1464",
            "392",
            "693",
            "1436",
            "819",
            "363",
            "648",
            "838",
            "517",
            "1629",
            "689",
            "1443",
            "71",
            "448",
            "36",
            "1698",
            "108",
            "1944",
            "755",
            "1428",
            "67",
            "2055",
            "1939",
            "1657"
        ],
        "SKUs": [
            "435",
            "890",
            "104",
            "953",
            "952",
            "769",
            "516",
            "611",
            "391",
            "343",
            "372",
            "805",
            "94",
            "687",
            "521",
            "517",
            "280",
            "998",
            "379",
            "891",
            "390",
            "237",
            "243",
            "480",
            "93",
            "420",
            "992",
            "118",
            "479",
            "612",
            "520",
            "392",
            "827",
            "828",
            "238",
            "478",
            "515",
            "117",
            "997",
            "975",
            "103"
        ],
        "distance": 224.142578125,
        "computational_time": 249.976377
    },
    "batch_15": {
        "orders": [
            "18",
            "27",
            "30",
            "39",
            "135",
            "153",
            "177",
            "195",
            "207",
            "255",
            "273",
            "279",
            "285",
            "288",
            "312",
            "336",
            "363",
            "369",
            "375",
            "378",
            "390",
            "429",
            "447",
            "456",
            "493"
        ],
        "pickRoute": [
            "1166",
            "360",
            "551",
            "1926",
            "1926",
            "19",
            "1077",
            "1780",
            "1563",
            "2170",
            "600",
            "1038",
            "327",
            "405",
            "598",
            "328",
            "547",
            "661",
            "2085",
            "923",
            "869",
            "284",
            "1560",
            "2054",
            "22",
            "1984",
            "1266",
            "2133",
            "1900",
            "992",
            "495",
            "1547",
            "1130",
            "782",
            "1650",
            "252",
            "8",
            "1032",
            "1382",
            "540",
            "254",
            "678",
            "1725",
            "493",
            "44",
            "1986",
            "2043",
            "1521",
            "1971",
            "1261",
            "1757",
            "1151",
            "720",
            "1405",
            "1954",
            "976",
            "1990",
            "556",
            "1726",
            "1539",
            "294",
            "249",
            "45",
            "2038",
            "857",
            "713"
        ],
        "SKUs": [
            "1010",
            "1008",
            "800",
            "55",
            "55",
            "591",
            "940",
            "576",
            "394",
            "577",
            "563",
            "76",
            "770",
            "643",
            "523",
            "562",
            "744",
            "31",
            "771",
            "423",
            "561",
            "311",
            "275",
            "522",
            "880",
            "765",
            "77",
            "754",
            "358",
            "742",
            "596",
            "692",
            "52",
            "881",
            "644",
            "798",
            "917",
            "422",
            "33",
            "575",
            "276",
            "393",
            "918",
            "312",
            "359",
            "32",
            "693",
            "919",
            "595",
            "421",
            "310",
            "926",
            "645",
            "941",
            "524",
            "942",
            "360",
            "879",
            "743",
            "799",
            "691",
            "274",
            "772",
            "395",
            "905",
            "1009"
        ],
        "distance": 289.66015625,
        "computational_time": 248.813734
    },
    "batch_16": {
        "orders": [
            "1",
            "7",
            "28",
            "46",
            "109",
            "142",
            "148",
            "163",
            "166",
            "169",
            "223",
            "247",
            "265",
            "283",
            "316",
            "361",
            "373",
            "388",
            "412",
            "418",
            "421",
            "445",
            "454",
            "466",
            "481"
        ],
        "pickRoute": [
            "457",
            "990",
            "151",
            "485",
            "2108",
            "594",
            "145",
            "2135",
            "1354",
            "921",
            "1308",
            "519",
            "1088",
            "1810",
            "1092",
            "2145",
            "1556",
            "176",
            "439",
            "1866",
            "890",
            "894",
            "1213",
            "243",
            "105",
            "930",
            "879",
            "879",
            "1470",
            "1730",
            "699",
            "68",
            "130",
            "319"
        ],
        "SKUs": [
            "92",
            "935",
            "53",
            "794",
            "506",
            "452",
            "859",
            "337",
            "585",
            "856",
            "936",
            "505",
            "738",
            "845",
            "586",
            "959",
            "504",
            "763",
            "12",
            "331",
            "987",
            "545",
            "2",
            "342",
            "934",
            "587",
            "652",
            "652",
            "300",
            "913",
            "855",
            "223",
            "739",
            "289"
        ],
        "distance": 142.4609375,
        "computational_time": 248.897078
    },
    "batch_17": {
        "orders": [
            "17",
            "20",
            "23",
            "89",
            "107",
            "128",
            "131",
            "134",
            "152",
            "260",
            "299",
            "302",
            "332",
            "338",
            "350",
            "353",
            "359",
            "362",
            "385",
            "386",
            "395",
            "398",
            "446",
            "458",
            "467"
        ],
        "pickRoute": [
            "1928",
            "287",
            "107",
            "435",
            "125",
            "127",
            "390",
            "775",
            "692",
            "1402",
            "790",
            "999",
            "498",
            "1806",
            "1816",
            "470",
            "700",
            "944",
            "84",
            "1458",
            "420",
            "1670",
            "1190",
            "2116",
            "987",
            "1769",
            "1903",
            "817",
            "461",
            "1711",
            "1210",
            "1393",
            "1549",
            "1549",
            "1504",
            "369",
            "708",
            "683",
            "2111",
            "1638",
            "654",
            "1996",
            "2161",
            "1484",
            "1497",
            "226",
            "1794",
            "1329",
            "590",
            "2141",
            "1139",
            "1587",
            "924",
            "1544",
            "949",
            "1708"
        ],
        "SKUs": [
            "535",
            "308",
            "790",
            "947",
            "260",
            "262",
            "719",
            "915",
            "220",
            "740",
            "29",
            "626",
            "45",
            "961",
            "720",
            "618",
            "273",
            "696",
            "627",
            "685",
            "261",
            "267",
            "946",
            "37",
            "221",
            "724",
            "534",
            "945",
            "619",
            "806",
            "718",
            "30",
            "788",
            "788",
            "962",
            "44",
            "309",
            "38",
            "272",
            "815",
            "178",
            "741",
            "219",
            "734",
            "916",
            "814",
            "179",
            "726",
            "789",
            "628",
            "960",
            "914",
            "725",
            "686",
            "791",
            "813"
        ],
        "distance": 228.287109375,
        "computational_time": 249.745995
    },
    "batch_18": {
        "orders": [
            "10",
            "25",
            "31",
            "34",
            "100",
            "136",
            "157",
            "172",
            "181",
            "193",
            "226",
            "241",
            "262",
            "292",
            "295",
            "301",
            "310",
            "325",
            "370",
            "376",
            "379",
            "391",
            "409",
            "427",
            "487"
        ],
        "pickRoute": [
            "1813",
            "1527",
            "1801",
            "1946",
            "169",
            "1313",
            "364",
            "96",
            "571",
            "1036",
            "1959",
            "104",
            "611",
            "1689",
            "1111",
            "1661",
            "1933",
            "489",
            "1737",
            "1826",
            "2079",
            "1691",
            "938",
            "1848",
            "7",
            "866",
            "345",
            "1776",
            "1330",
            "604",
            "1718",
            "613",
            "1772",
            "18",
            "221",
            "1075",
            "721",
            "357",
            "62",
            "1205",
            "277",
            "1328",
            "1834",
            "1224",
            "2025",
            "1828",
            "158",
            "1615",
            "959",
            "486",
            "187",
            "916",
            "83",
            "1732",
            "1389",
            "1095",
            "229",
            "1686",
            "633",
            "2144",
            "647",
            "414",
            "842",
            "806",
            "1305",
            "1578",
            "2091",
            "1310",
            "2125",
            "1116",
            "354",
            "793",
            "941"
        ],
        "SKUs": [
            "541",
            "66",
            "65",
            "625",
            "388",
            "539",
            "773",
            "875",
            "57",
            "873",
            "58",
            "16",
            "774",
            "995",
            "201",
            "669",
            "623",
            "756",
            "177",
            "603",
            "457",
            "767",
            "346",
            "491",
            "319",
            "202",
            "15",
            "609",
            "640",
            "49",
            "755",
            "458",
            "389",
            "540",
            "321",
            "608",
            "279",
            "492",
            "668",
            "667",
            "795",
            "175",
            "50",
            "347",
            "277",
            "200",
            "838",
            "320",
            "348",
            "639",
            "768",
            "602",
            "604",
            "840",
            "387",
            "801",
            "278",
            "775",
            "493",
            "996",
            "874",
            "56",
            "64",
            "766",
            "368",
            "839",
            "638",
            "802",
            "757",
            "610",
            "48",
            "624",
            "459"
        ],
        "distance": 303.359375,
        "computational_time": 250.863838
    },
    "batch_19": {
        "orders": [
            "21",
            "36",
            "66",
            "78",
            "105",
            "111",
            "114",
            "174",
            "210",
            "237",
            "240",
            "264",
            "282",
            "294",
            "303",
            "327",
            "357",
            "360",
            "396",
            "411",
            "417",
            "423",
            "435",
            "468",
            "480"
        ],
        "pickRoute": [
            "133",
            "880",
            "203",
            "1795",
            "1252",
            "1690",
            "263",
            "1748",
            "741",
            "1630",
            "749",
            "242",
            "387",
            "1138",
            "79",
            "374",
            "1753",
            "544",
            "783",
            "316",
            "943",
            "981",
            "335",
            "918",
            "1267",
            "1094",
            "552",
            "2048",
            "2160",
            "652",
            "927",
            "588",
            "1694",
            "150",
            "795",
            "1619",
            "1583",
            "597",
            "1884",
            "2071",
            "686",
            "759",
            "904",
            "2046",
            "1372",
            "441",
            "711",
            "2078",
            "1704",
            "1764",
            "585",
            "1506",
            "561",
            "791",
            "1243"
        ],
        "SKUs": [
            "226",
            "735",
            "986",
            "893",
            "227",
            "584",
            "488",
            "629",
            "737",
            "482",
            "233",
            "732",
            "544",
            "863",
            "428",
            "892",
            "607",
            "672",
            "965",
            "809",
            "736",
            "131",
            "213",
            "153",
            "69",
            "843",
            "215",
            "39",
            "70",
            "353",
            "854",
            "864",
            "352",
            "963",
            "154",
            "853",
            "964",
            "583",
            "671",
            "481",
            "844",
            "543",
            "474",
            "808",
            "214",
            "155",
            "490",
            "582",
            "41",
            "489",
            "731",
            "40",
            "71",
            "807",
            "429"
        ],
        "distance": 261.728515625,
        "computational_time": 249.104755
    },
    "batch_20": {
        "orders": [
            "26",
            "32",
            "51",
            "57",
            "84",
            "98",
            "99",
            "117",
            "129",
            "132",
            "204",
            "215",
            "252",
            "258",
            "330",
            "351",
            "366",
            "372",
            "414",
            "432",
            "440",
            "441",
            "459",
            "471",
            "474"
        ],
        "pickRoute": [
            "1268",
            "857",
            "1559",
            "1186",
            "1175",
            "1979",
            "148",
            "347",
            "1466",
            "818",
            "1119",
            "1176",
            "619",
            "1158",
            "1003",
            "920",
            "1383",
            "1693",
            "743",
            "1486",
            "906",
            "1843",
            "1892",
            "1896",
            "1523",
            "758",
            "1452",
            "1649",
            "174",
            "350",
            "984",
            "1165",
            "142",
            "529",
            "809",
            "1640",
            "972",
            "227",
            "259",
            "157",
            "1844",
            "2163",
            "1771",
            "1145",
            "1557",
            "1953",
            "2015",
            "603",
            "64"
        ],
        "SKUs": [
            "61",
            "905",
            "414",
            "240",
            "949",
            "112",
            "99",
            "171",
            "681",
            "198",
            "721",
            "907",
            "416",
            "98",
            "749",
            "760",
            "762",
            "263",
            "530",
            "761",
            "114",
            "199",
            "268",
            "679",
            "680",
            "847",
            "415",
            "948",
            "722",
            "113",
            "518",
            "239",
            "906",
            "976",
            "170",
            "972",
            "886",
            "531",
            "97",
            "750",
            "438",
            "904",
            "60",
            "196",
            "51",
            "437",
            "59",
            "436",
            "197"
        ],
        "distance": 266.373046875,
        "computational_time": 249.842212
    }
}