{
    "batch_1": {
        "orders": [
            "1",
            "4",
            "16",
            "28",
            "40",
            "46",
            "70",
            "79",
            "103",
            "106",
            "127"
        ],
        "pickRoute": [
            "404",
            "1993",
            "317",
            "317",
            "662",
            "169",
            "1793",
            "956",
            "601",
            "1308",
            "1087",
            "1200",
            "1111",
            "550",
            "1519",
            "1274",
            "1388",
            "2045",
            "1389",
            "1665",
            "510",
            "2053",
            "1786",
            "158",
            "1981",
            "2032",
            "1894",
            "90"
        ],
        "SKUs": [
            "4",
            "11",
            "57",
            "57",
            "173",
            "229",
            "86",
            "231",
            "275",
            "221",
            "152",
            "32",
            "56",
            "10",
            "98",
            "150",
            "87",
            "172",
            "276",
            "3",
            "151",
            "97",
            "33",
            "2",
            "31",
            "96",
            "230",
            "222"
        ],
        "distance": 164.080078125,
        "computational_time": 14.734993
    },
    "batch_2": {
        "orders": [
            "11",
            "71",
            "85",
            "98",
            "101"
        ],
        "pickRoute": [
            "390",
            "1849",
            "1436",
            "1941",
            "2131",
            "1230",
            "1190",
            "1711"
        ],
        "SKUs": [
            "219",
            "153",
            "154",
            "184",
            "213",
            "212",
            "22",
            "185"
        ],
        "distance": 139.537109375,
        "computational_time": 15.007651
    },
    "batch_3": {
        "orders": [
            "7",
            "13",
            "25",
            "49",
            "52",
            "58",
            "61",
            "82",
            "121",
            "130",
            "145"
        ],
        "pickRoute": [
            "1323",
            "1140",
            "1888",
            "1227",
            "2152",
            "1955",
            "1450",
            "1537",
            "666",
            "1683",
            "1821",
            "750",
            "1322",
            "54",
            "375",
            "1846",
            "251",
            "1866",
            "1828",
            "171"
        ],
        "SKUs": [
            "26",
            "264",
            "122",
            "104",
            "112",
            "111",
            "50",
            "279",
            "127",
            "177",
            "16",
            "49",
            "258",
            "179",
            "123",
            "310",
            "126",
            "105",
            "113",
            "178"
        ],
        "distance": 132.58984375,
        "computational_time": 14.958763
    },
    "batch_4": {
        "orders": [
            "6",
            "18",
            "27",
            "63",
            "66",
            "72",
            "87",
            "126",
            "138",
            "144",
            "147"
        ],
        "pickRoute": [
            "644",
            "922",
            "148",
            "2047",
            "41",
            "257",
            "650",
            "992",
            "1020",
            "1780",
            "2011",
            "1032",
            "16",
            "1552",
            "1986",
            "441",
            "968",
            "42",
            "230",
            "246",
            "1258",
            "1473",
            "1798",
            "430",
            "400",
            "976",
            "1604",
            "1205",
            "1207",
            "1439",
            "1343"
        ],
        "SKUs": [
            "133",
            "54",
            "35",
            "308",
            "14",
            "312",
            "313",
            "36",
            "187",
            "309",
            "295",
            "141",
            "15",
            "132",
            "273",
            "296",
            "13",
            "189",
            "55",
            "140",
            "188",
            "307",
            "37",
            "156",
            "143",
            "274",
            "155",
            "131",
            "142",
            "294",
            "157"
        ],
        "distance": 228.37890625,
        "computational_time": 14.885886
    },
    "batch_5": {
        "orders": [
            "3",
            "8",
            "9",
            "12",
            "24",
            "38",
            "41",
            "81",
            "93",
            "114",
            "120"
        ],
        "pickRoute": [
            "1814",
            "2028",
            "857",
            "1010",
            "1336",
            "551",
            "463",
            "365",
            "2142",
            "883",
            "791",
            "1524",
            "2076",
            "503",
            "498",
            "1380"
        ],
        "SKUs": [
            "17",
            "25",
            "8",
            "263",
            "176",
            "268",
            "9",
            "24",
            "250",
            "48",
            "201",
            "18",
            "23",
            "82",
            "88",
            "81"
        ],
        "distance": 199.837890625,
        "computational_time": 14.996045
    },
    "batch_6": {
        "orders": [
            "17",
            "29",
            "53",
            "62",
            "74",
            "83",
            "92",
            "94",
            "95",
            "107",
            "137"
        ],
        "pickRoute": [
            "68",
            "212",
            "108",
            "1278",
            "532",
            "1514",
            "421",
            "1481",
            "501",
            "1989",
            "964",
            "1893",
            "817",
            "1917",
            "1455",
            "1428",
            "513",
            "687",
            "1103",
            "1103",
            "215",
            "473",
            "1407",
            "325",
            "496",
            "1427",
            "1501",
            "548"
        ],
        "SKUs": [
            "203",
            "204",
            "115",
            "205",
            "292",
            "180",
            "34",
            "200",
            "232",
            "129",
            "160",
            "58",
            "207",
            "234",
            "130",
            "199",
            "114",
            "59",
            "206",
            "206",
            "233",
            "293",
            "128",
            "60",
            "181",
            "161",
            "162",
            "202"
        ],
        "distance": 181.154296875,
        "computational_time": 14.847966
    },
    "batch_7": {
        "orders": [
            "19",
            "37",
            "43",
            "55",
            "67",
            "73",
            "76",
            "109",
            "112",
            "136",
            "142"
        ],
        "pickRoute": [
            "358",
            "25",
            "1040",
            "1325",
            "1150",
            "772",
            "617",
            "2137",
            "1718",
            "18",
            "1385",
            "400",
            "1935",
            "1255",
            "101",
            "1095",
            "162",
            "2040",
            "2081",
            "1487",
            "1429",
            "110",
            "1310",
            "296"
        ],
        "SKUs": [
            "304",
            "158",
            "245",
            "80",
            "78",
            "91",
            "144",
            "159",
            "79",
            "291",
            "246",
            "143",
            "40",
            "119",
            "167",
            "303",
            "39",
            "238",
            "145",
            "38",
            "290",
            "166",
            "168",
            "247"
        ],
        "distance": 172.546875,
        "computational_time": 14.815599
    },
    "batch_8": {
        "orders": [
            "21",
            "35",
            "51",
            "54",
            "75",
            "84",
            "102",
            "105",
            "108",
            "135",
            "141"
        ],
        "pickRoute": [
            "387",
            "995",
            "624",
            "677",
            "669",
            "669",
            "1459",
            "3",
            "1562",
            "1583",
            "592",
            "1377",
            "92",
            "832",
            "925",
            "213",
            "1066",
            "1938",
            "1856",
            "728",
            "1467",
            "1739",
            "1871",
            "1439",
            "197",
            "1281",
            "234",
            "2090"
        ],
        "SKUs": [
            "110",
            "240",
            "228",
            "235",
            "220",
            "220",
            "165",
            "43",
            "289",
            "118",
            "109",
            "237",
            "300",
            "182",
            "226",
            "183",
            "302",
            "116",
            "227",
            "117",
            "164",
            "236",
            "301",
            "294",
            "163",
            "74",
            "72",
            "73"
        ],
        "distance": 251.796875,
        "computational_time": 14.702171
    },
    "batch_9": {
        "orders": [
            "5",
            "23",
            "30",
            "44",
            "59",
            "104",
            "113",
            "116",
            "134",
            "139",
            "140"
        ],
        "pickRoute": [
            "1932",
            "1814",
            "627",
            "1742",
            "2073",
            "2154",
            "1921",
            "2069",
            "790",
            "1193",
            "1464",
            "470",
            "864",
            "420",
            "1666",
            "1495",
            "159",
            "107",
            "50",
            "602"
        ],
        "SKUs": [
            "298",
            "17",
            "61",
            "297",
            "12",
            "256",
            "299",
            "124",
            "225",
            "254",
            "47",
            "255",
            "223",
            "249",
            "287",
            "224",
            "248",
            "46",
            "92",
            "288"
        ],
        "distance": 164.712890625,
        "computational_time": 14.978817
    },
    "batch_10": {
        "orders": [
            "31",
            "36",
            "45",
            "48",
            "60",
            "90",
            "96",
            "111",
            "117",
            "123",
            "132"
        ],
        "pickRoute": [
            "1301",
            "551",
            "10",
            "1547",
            "442",
            "1851",
            "786",
            "2011",
            "279",
            "2132",
            "1972",
            "841",
            "887",
            "241",
            "2113",
            "1833",
            "560",
            "1918",
            "549",
            "1778",
            "1398",
            "1865",
            "1677",
            "1322",
            "199",
            "45",
            "200",
            "1814",
            "890"
        ],
        "SKUs": [
            "63",
            "268",
            "77",
            "125",
            "244",
            "194",
            "208",
            "295",
            "283",
            "101",
            "95",
            "282",
            "257",
            "76",
            "267",
            "196",
            "242",
            "103",
            "102",
            "243",
            "94",
            "195",
            "75",
            "258",
            "209",
            "193",
            "93",
            "17",
            "62"
        ],
        "distance": 232.126953125,
        "computational_time": 14.93975
    },
    "batch_11": {
        "orders": [
            "15",
            "22",
            "33",
            "39",
            "42",
            "57",
            "69",
            "78",
            "91",
            "99",
            "129"
        ],
        "pickRoute": [
            "1299",
            "133",
            "1447",
            "79",
            "943",
            "2119",
            "2119",
            "1283",
            "522",
            "522",
            "773",
            "1298",
            "1569",
            "761",
            "1833",
            "1214",
            "1931",
            "1947",
            "1990",
            "450",
            "406",
            "1982",
            "721",
            "959"
        ],
        "SKUs": [
            "198",
            "170",
            "171",
            "68",
            "149",
            "84",
            "84",
            "29",
            "197",
            "197",
            "90",
            "214",
            "278",
            "89",
            "196",
            "85",
            "216",
            "67",
            "215",
            "121",
            "30",
            "83",
            "45",
            "44"
        ],
        "distance": 220.986328125,
        "computational_time": 14.787435
    },
    "batch_12": {
        "orders": [
            "10",
            "34",
            "64",
            "88",
            "97",
            "100",
            "115",
            "118",
            "124",
            "133",
            "148"
        ],
        "pickRoute": [
            "813",
            "1886",
            "1192",
            "239",
            "1684",
            "323",
            "1313",
            "787",
            "2144",
            "285",
            "86",
            "1279",
            "2045",
            "1247",
            "933",
            "1854",
            "2017",
            "820",
            "1084",
            "1129",
            "2147",
            "1662",
            "1489",
            "644",
            "979",
            "1751",
            "1917",
            "50",
            "163",
            "1438",
            "1526",
            "937",
            "1287",
            "919"
        ],
        "SKUs": [
            "269",
            "135",
            "260",
            "217",
            "285",
            "314",
            "316",
            "70",
            "19",
            "191",
            "251",
            "211",
            "172",
            "20",
            "134",
            "252",
            "315",
            "210",
            "259",
            "284",
            "286",
            "270",
            "69",
            "133",
            "253",
            "136",
            "234",
            "92",
            "71",
            "190",
            "175",
            "218",
            "271",
            "21"
        ],
        "distance": 224.587890625,
        "computational_time": 14.671509
    },
    "batch_13": {
        "orders": [
            "2",
            "26",
            "32",
            "47",
            "50",
            "56",
            "65",
            "68",
            "89",
            "125",
            "143"
        ],
        "pickRoute": [
            "1482",
            "1118",
            "1705",
            "2059",
            "909",
            "668",
            "1211",
            "1941",
            "1465",
            "913",
            "84",
            "683",
            "1201",
            "1922",
            "838",
            "1262",
            "517",
            "859",
            "1647",
            "1995",
            "2165",
            "2112",
            "1443",
            "415",
            "417",
            "1132"
        ],
        "SKUs": [
            "137",
            "106",
            "51",
            "108",
            "146",
            "64",
            "52",
            "184",
            "5",
            "306",
            "66",
            "99",
            "139",
            "120",
            "100",
            "148",
            "272",
            "7",
            "192",
            "305",
            "65",
            "107",
            "53",
            "147",
            "6",
            "138"
        ],
        "distance": 164.576171875,
        "computational_time": 14.761206
    },
    "batch_14": {
        "orders": [
            "14",
            "20",
            "77",
            "80",
            "86",
            "110",
            "119",
            "122",
            "128",
            "131",
            "146"
        ],
        "pickRoute": [
            "995",
            "1547",
            "450",
            "440",
            "882",
            "369",
            "1711",
            "1867",
            "67",
            "774",
            "1456",
            "935",
            "1526",
            "2105",
            "1685",
            "1332",
            "641",
            "483",
            "1320",
            "2077",
            "1544",
            "514"
        ],
        "SKUs": [
            "240",
            "125",
            "121",
            "266",
            "27",
            "41",
            "185",
            "186",
            "281",
            "239",
            "277",
            "280",
            "175",
            "265",
            "174",
            "42",
            "262",
            "311",
            "169",
            "261",
            "28",
            "241"
        ],
        "distance": 219.650390625,
        "computational_time": 14.910909
    }
}